daksh/__init__.py
daksh/__pre_init__.py
daksh/health.py
daksh/update_prompts.py
daksh/assets/copilot-instructions.md
daksh/assets/extra.css
daksh/assets/index.md
daksh/assets/mkdocs.yml
daksh/assets/mkdocs_deps.txt
daksh/assets/run-mkdocs.sh
daksh/assets/daksh-prompts/language-specific-guidelines/python/environments.md
daksh/assets/daksh-prompts/language-specific-guidelines/typescript/coding-instructions.md
daksh/assets/daksh-prompts/prompts/00-user-personas/00-User-Personas.chatmode.md
daksh/assets/daksh-prompts/prompts/000-market-research/0-Market-Research.chatmode.md
daksh/assets/daksh-prompts/prompts/10-vision/1 - Vision Document.chatmode.md
daksh/assets/daksh-prompts/prompts/20-business/2 - Business Requirement Overview.chatmode.md
daksh/assets/daksh-prompts/prompts/30-roadmap/3 - Implementation Roadmap.chatmode.md
daksh/assets/daksh-prompts/prompts/40-module/4 - Module PRD TRD and Tasks.chatmode.md
daksh/assets/daksh-prompts/prompts/40-module/4a - PRD.chatmode.md
daksh/assets/daksh-prompts/prompts/40-module/4b - TRD.chatmode.md
daksh/assets/daksh-prompts/prompts/40-module/4c - Dev Tasks.chatmode.md
daksh/assets/daksh-prompts/prompts/50-implementation/5 - Implement.chatmode.md
daksh/assets/json-files/mcp.json
daksh/assets/json-files/settings.json
daksh/assets/json-files/tasks.json
daksh/assets/overrides/mermaid-config.js
daksh-0.7.0.dist-info/licenses/AUTHORS.md
daksh-0.7.0.dist-info/licenses/LICENSE
daksh-0.7.0.dist-info/METADATA
daksh-0.7.0.dist-info/WHEEL
daksh-0.7.0.dist-info/entry_points.txt
daksh-0.7.0.dist-info/top_level.txt
daksh-0.7.0.dist-info/RECORD
