Metadata-Version: 2.4
Name: daksh
Version: 0.7.0
Summary: Documentation & Artifact Knowledge Synchronization Hub
Author-email: Yeshwanth Reddy <yeshwanth@divami.com>
Maintainer-email: Yeshwanth Reddy <yeshwanth@divami.com>
License: MIT license
Project-URL: bugs, https://github.com/yeshwanth-divami/daksh/issues
Project-URL: changelog, https://github.com/yeshwanth-divami/daksh/blob/master/changelog.md
Project-URL: homepage, https://github.com/yeshwanth-divami/daksh
License-File: LICENSE
License-File: AUTHORS.md
Requires-Dist: typer
Requires-Dist: nbdev
Provides-Extra: dev
Requires-Dist: coverage; extra == "dev"
Requires-Dist: mypy; extra == "dev"
Requires-Dist: pytest; extra == "dev"
Requires-Dist: ruff; extra == "dev"
Dynamic: license-file
